mizarlabs/__init__.py
mizarlabs/static.py
mizarlabs/model/__init__.py
mizarlabs/model/bootstrapping.py
mizarlabs/model/model_selection.py
mizarlabs/model/pipeline.py
mizarlabs/model/sequentially_bootstrapped_bagging_classifier.py
mizarlabs/structural_breaks/__init__.py
mizarlabs/structural_breaks/cusum_chu_stinchcome_white.py
mizarlabs/structural_breaks/sadf.py
mizarlabs/structural_breaks/sdfc.py
mizarlabs/tests/__init__.py
mizarlabs/tests/conftest.py
mizarlabs/transformers/__init__.py
mizarlabs/transformers/utils.py
mizarlabs/transformers/features/__init__.py
mizarlabs/transformers/features/custom.py
mizarlabs/transformers/features/rolling_z_score.py
mizarlabs/transformers/microstructural_features/__init__.py
mizarlabs/transformers/microstructural_features/first_generation.py
mizarlabs/transformers/microstructural_features/second_generation.py
mizarlabs/transformers/microstructural_features/vpin.py
mizarlabs/transformers/sample_weights/__init__.py
mizarlabs/transformers/sampling/__init__.py
mizarlabs/transformers/sampling/average_uniqueness.py
mizarlabs/transformers/sampling/down_sampling.py
mizarlabs/transformers/targets/__init__.py
mizarlabs/transformers/targets/labeling.py
mizarlabs/transformers/targets/trend_scanning.py
mizarlabs/transformers/technical/__init__.py
mizarlabs/transformers/technical/factory.py
mizarlabs/transformers/technical/macd.py
mizarlabs/transformers/technical/mean_reversion.py
mizarlabs/transformers/technical/moving_average.py
mizarlabs/transformers/technical/rsi.py
mizarlabs/transformers/technical/volume.py
mizarlabs/transformers/trading/__init__.py
mizarlabs/transformers/trading/bet_sizing.py
mizar_labs-0.2.3.dist-info/LICENSE
mizar_labs-0.2.3.dist-info/METADATA
mizar_labs-0.2.3.dist-info/WHEEL
mizar_labs-0.2.3.dist-info/top_level.txt
mizar_labs-0.2.3.dist-info/RECORD
