Metadata-Version: 2.1
Name: mizar-labs
Version: 0.2.3
Summary: Package for building financial machine learning models
Home-page: https://github.com/MizarAI/mizar-labs
Author: MizarAI
Author-email: info@mizar.ai
License: UNKNOWN
Project-URL: Bug Tracker, https://github.com/MizarAI/mizar-labs/issues
Platform: UNKNOWN
Requires-Python: >=3.8
License-File: LICENSE
Requires-Dist: pandas (>=1.2.2)
Requires-Dist: scikit-learn (>=0.24.1)
Requires-Dist: numba (>=0.52.0)
Requires-Dist: ta-lib (>=0.4.19)
Requires-Dist: pytest (>=6.2.2)
